detrain/__init__.py
detrain/fsdp_tp/__init__.py
detrain/fsdp_tp/evaluation.py
detrain/fsdp_tp/log_utils.py
detrain/fsdp_tp/mesh_utils.py
detrain/fsdp_tp/model_2d.py
detrain/fsdp_tp/train.py
detrain/fsdp_tp/train_eval.py
detrain/ppl/__init__.py
detrain/ppl/args_util.py
detrain/ppl/dataset_util.py
detrain/ppl/dis_model.py
detrain/ppl/evaluation.py
detrain/ppl/master_node.py
detrain/ppl/train.py
detrain/ppl/worker.py
detrain/tp/__init__.py
detrain/tp/evaluation.py
detrain/tp/model_utils.py
detrain/tp/sequence_evaluation.py
detrain/tp/sequence_train.py
detrain/tp/sequence_train_eval.py
detrain/tp/train.py
detrain/tp/train_eval.py
detrain-0.2.6.dist-info/METADATA
detrain-0.2.6.dist-info/WHEEL
detrain-0.2.6.dist-info/top_level.txt
detrain-0.2.6.dist-info/RECORD
