Metadata-Version: 2.1
Name: detrain
Version: 0.2.6
Summary: A package for distributed training & model parallelism using Torch
Author: A2N Finance
Author-email: Levi <levi@a2n.finance>, John <john@a2n.finance>
License: MIT
Keywords: torch,model parallelism,pipeline,tensor
Classifier: Programming Language :: Python :: 3
Requires-Python: >=3.8
Requires-Dist: torch
